.bumpversion.cfg
CONTRIBUTING.md
LICENSE
MANIFEST.in
Makefile
README.md
pyproject.toml
python_junit.xml
setup.py
Pytorch_nlp_Chatbot.egg-info/PKG-INFO
Pytorch_nlp_Chatbot.egg-info/SOURCES.txt
Pytorch_nlp_Chatbot.egg-info/dependency_links.txt
Pytorch_nlp_Chatbot.egg-info/requires.txt
Pytorch_nlp_Chatbot.egg-info/top_level.txt
chatbot/__init__.py
chatbot/models.py
chatbot/tests/__init__.py
chatbot/tests/test_models.py